<?xml version="1.0" encoding="utf-8" ?>
<dwsync>
<file name="jquery.spectrum-de.js" server="D:/Dropbox/CharisTech/Project Backups/Aux-Digital/" local="131334078640000000" remote="131334078640000000" Dst="1" />
<file name="jquery.spectrum-dk.js" server="D:/Dropbox/CharisTech/Project Backups/Aux-Digital/" local="131334078640000000" remote="131334078640000000" Dst="1" />
<file name="jquery.spectrum-es.js" server="D:/Dropbox/CharisTech/Project Backups/Aux-Digital/" local="131334078630000000" remote="131334078630000000" Dst="1" />
<file name="jquery.spectrum-fa.js" server="D:/Dropbox/CharisTech/Project Backups/Aux-Digital/" local="131334078640000000" remote="131334078640000000" Dst="1" />
<file name="jquery.spectrum-fi.js" server="D:/Dropbox/CharisTech/Project Backups/Aux-Digital/" local="131334078640000000" remote="131334078640000000" Dst="1" />
<file name="jquery.spectrum-fr.js" server="D:/Dropbox/CharisTech/Project Backups/Aux-Digital/" local="131334078640000000" remote="131334078640000000" Dst="1" />
<file name="jquery.spectrum-gr.js" server="D:/Dropbox/CharisTech/Project Backups/Aux-Digital/" local="131334078630000000" remote="131334078630000000" Dst="1" />
<file name="jquery.spectrum-he.js" server="D:/Dropbox/CharisTech/Project Backups/Aux-Digital/" local="131334078640000000" remote="131334078640000000" Dst="1" />
<file name="jquery.spectrum-hr.js" server="D:/Dropbox/CharisTech/Project Backups/Aux-Digital/" local="131334078640000000" remote="131334078640000000" Dst="1" />
<file name="jquery.spectrum-it.js" server="D:/Dropbox/CharisTech/Project Backups/Aux-Digital/" local="131334078640000000" remote="131334078640000000" Dst="1" />
<file name="jquery.spectrum-ja.js" server="D:/Dropbox/CharisTech/Project Backups/Aux-Digital/" local="131334078640000000" remote="131334078640000000" Dst="1" />
<file name="jquery.spectrum-nl.js" server="D:/Dropbox/CharisTech/Project Backups/Aux-Digital/" local="131334078630000000" remote="131334078630000000" Dst="1" />
<file name="jquery.spectrum-pl.js" server="D:/Dropbox/CharisTech/Project Backups/Aux-Digital/" local="131334078640000000" remote="131334078640000000" Dst="1" />
<file name="jquery.spectrum-pt-br.js" server="D:/Dropbox/CharisTech/Project Backups/Aux-Digital/" local="131334078640000000" remote="131334078640000000" Dst="1" />
<file name="jquery.spectrum-ru.js" server="D:/Dropbox/CharisTech/Project Backups/Aux-Digital/" local="131334078630000000" remote="131334078630000000" Dst="1" />
<file name="jquery.spectrum-sv.js" server="D:/Dropbox/CharisTech/Project Backups/Aux-Digital/" local="131334078640000000" remote="131334078640000000" Dst="1" />
<file name="jquery.spectrum-tr.js" server="D:/Dropbox/CharisTech/Project Backups/Aux-Digital/" local="131334078630000000" remote="131334078630000000" Dst="1" />
<file name="jquery.spectrum-zh-cn.js" server="D:/Dropbox/CharisTech/Project Backups/Aux-Digital/" local="131334078630000000" remote="131334078630000000" Dst="1" />
<file name="jquery.spectrum-zh-tw.js" server="D:/Dropbox/CharisTech/Project Backups/Aux-Digital/" local="131334078640000000" remote="131334078640000000" Dst="1" />
</dwsync>